tap_google_analytics/__init__.py
tap_google_analytics/error.py
tap_google_analytics/ga_client.py
tap_google_analytics/reports_helper.py
tap_google_analytics/defaults/default_report_definition.json
pipelinewise_tap_google_analytics-1.1.1.dist-info/LICENSE
pipelinewise_tap_google_analytics-1.1.1.dist-info/METADATA
pipelinewise_tap_google_analytics-1.1.1.dist-info/WHEEL
pipelinewise_tap_google_analytics-1.1.1.dist-info/entry_points.txt
pipelinewise_tap_google_analytics-1.1.1.dist-info/top_level.txt
pipelinewise_tap_google_analytics-1.1.1.dist-info/RECORD
