Metadata-Version: 2.1
Name: pipelinewise-tap-google-analytics
Version: 1.1.1
Summary: Singer.io tap for extracting data from the Google Analytics Reporting API
Home-page: https://gitlab.com/transferwise/pipelinewise-tap-google-analytics
Author: Meltano Team & Contributors
License: UNKNOWN
Platform: UNKNOWN
Classifier: License :: OSI Approved :: Apache Software License
Classifier: Programming Language :: Python :: 3 :: Only
Requires-Dist: pipelinewise-singer-python (==1.*)
Requires-Dist: google-api-python-client (==1.7.9)
Requires-Dist: oauth2client (==4.1.3)
Requires-Dist: backoff (==1.8.0)
